{
    "name": "Python 3 selenium",
    "context": "..",
    "dockerFile": "Dockerfile",
    "settings": {
        "terminal.integrated.shell.linux": "/bin/bash",
        "python.pythonPath": "/usr/local/bin/python",
        "autoDocstring.docstringFormat": "numpy",
    },
    "extensions": [
        "ms-python.python", 
        "gruntfuggly.todo-tree",
        "njpwerner.autodocstring",
        "kevinrose.vsc-python-indent",
        "pkief.material-icon-theme",
        "formulahendry.code-runner",
    ]
}